KerasCrafterGPT/KerasCrafterGPT.py
KerasCrafterGPT/__init__.py
kerascraftergpt-0.0.2.dist-info/METADATA
kerascraftergpt-0.0.2.dist-info/WHEEL
kerascraftergpt-0.0.2.dist-info/top_level.txt
kerascraftergpt-0.0.2.dist-info/RECORD
