Metadata-Version: 2.4
Name: KerasCrafterGPT
Version: 0.0.2
Summary: Toolkit for building Keras models with the help of GPT
Home-page: https://github.com/joshyattridge/KerasCrafterGPT
Author: Joshua Attridge
Keywords: keras,gpt,tensorflow,openai,machine,learning,chatgpt,ai
Classifier: Development Status :: 1 - Planning
Classifier: Intended Audience :: Developers
Classifier: Programming Language :: Python :: 3
Classifier: Operating System :: Unix
Classifier: Operating System :: MacOS :: MacOS X
Classifier: Operating System :: Microsoft :: Windows
Requires-Dist: tensorflow
Requires-Dist: numpy
Requires-Dist: openai
Dynamic: author
Dynamic: classifier
Dynamic: description
Dynamic: description-content-type
Dynamic: home-page
Dynamic: keywords
Dynamic: requires-dist
Dynamic: summary
